{
  "palettes": {
    "default": [
      "#c6e48b",
      "#7bc96f",
      "#49af5d",
      "#2e8840",
      "#196127"
    ],
    "danger": [
      "rgb(255, 204, 204)",
      "rgb(255, 153, 153)",
      "rgb(255, 102, 102)",
      "rgb(255, 51, 51)",
      "rgb(255, 0, 0)",
      "rgb(204, 0, 0)",
      "rgb(153, 0, 0)",
      "rgb(102, 0, 0)",
      "rgb(51, 0, 0)",
      "rgb(25, 0, 0)"
    ],
    "fire": [
      "rgb(51, 51, 51)",
      "rgb(77, 26, 26)",
      "rgb(102, 26, 26)",
      "rgb(127, 38, 38)",
      "rgb(153, 51, 51)",
      "rgb(181, 61, 61)",
      "rgb(255, 0, 0)"
    ],
    "heat": [
      "rgb(128, 138, 166)",
      "rgb(77, 90, 128)",
      "rgb(51, 64, 114)",
      "rgb(25, 38, 99)",
      "rgb(0, 18, 77)",
      "rgb(0, 10, 51)",
      "rgb(255, 204, 204)",
      "rgb(255, 153, 153)",
      "rgb(255, 102, 102)",
      "rgb(255, 51, 51)",
      "rgb(255, 0, 0)",
      "rgb(204, 0, 0)"
    ],
    "heat2": [
      "rgb(204, 0, 0)",
      "rgb(255, 0, 0)",
      "rgb(255, 51, 51)",
      "rgb(255, 102, 102)",
      "rgb(255, 153, 153)",
      "rgb(255, 204, 204)",
      "rgb(128, 138, 166)",
      "rgb(77, 90, 128)",
      "rgb(51, 64, 114)",
      "rgb(25, 38, 99)",
      "rgb(0, 18, 77)",
      "rgb(0, 10, 51)"
    ],
    "heat3": [
      "rgb(204, 0, 0)",
      "rgb(170, 20, 20)",
      "rgb(140, 35, 35)",
      "rgb(110, 45, 45)",
      "rgb(80, 50, 50)",
      "rgb(51, 51, 51)",
      "rgb(50, 55, 75)",
      "rgb(40, 45, 90)",
      "rgb(30, 35, 100)",
      "rgb(15, 20, 80)",
      "rgb(5, 15, 60)",
      "rgb(0, 10, 51)"
    ],
    "work": [
      "rgb(128, 138, 166)",
      "rgb(77, 90, 128)",
      "rgb(51, 64, 114)",
      "rgb(25, 38, 99)",
      "rgb(0, 18, 77)",
      "rgb(0, 10, 51)"
    ],
    "tasks": [
      "rgb(166, 152, 128)",
      "rgb(128, 112, 80)",
      "rgb(114, 95, 51)",
      "rgb(99, 78, 25)",
      "rgb(77, 59, 0)",
      "rgb(51, 38, 0)"
    ],
    "gaming": [
      "rgb(51, 51, 51)",
      "rgb(77, 77, 77)",
      "rgb(102, 102, 102)",
      "rgb(160, 160, 160)",
      "rgb(217, 221, 222)",
      "rgb(150, 160, 180)",
      "rgb(80, 90, 120)",
      "rgb(40, 50, 80)",
      "rgb(20, 30, 60)",
      "rgb(0, 10, 26)"
    ],
    "metime": [
      "rgb(230, 221, 217)",
      "rgb(204, 188, 179)",
      "rgb(179, 157, 140)",
      "rgb(153, 127, 102)",
      "rgb(128, 103, 80)",
      "rgb(114, 85, 51)",
      "rgb(99, 67, 26)",
      "rgb(75, 47, 1)",
      "rgb(51, 33, 0)",
      "rgb(26, 16, 0)"
    ],
    "activate": [
      "rgb(51, 51, 51)",
      "rgb(77, 77, 77)",
      "rgb(102, 102, 102)",
      "rgb(128, 128, 128)",
      "rgb(153, 153, 153)",
      "rgb(255, 255, 255)"
    ]
  },
  "weekStartDay": 1,
  "weekDisplayMode": "odd",
  "separateMonths": true,
  "language": "en",
  "viewTabsVisibility": {
    "documentation": true,
    "heatmap-tracker": true,
    "heatmap-tracker-statistics": true,
    "legend": true
  }
}